proxly.py
proxly-0.1.4.dist-info/licenses/LICENSE
proxly-0.1.4.dist-info/METADATA
proxly-0.1.4.dist-info/WHEEL
proxly-0.1.4.dist-info/top_level.txt
proxly-0.1.4.dist-info/RECORD
